fedml/__init__.py
fedml/distributed/__init__.py
fedml/distributed/client/__init__.py
fedml/distributed/client/client_manager.py
fedml/distributed/communication/__init__.py
fedml/distributed/communication/com_manager.py
fedml/distributed/communication/message.py
fedml/distributed/communication/mpi_message.py
fedml/distributed/communication/mpi_receive_thread.py
fedml/distributed/communication/mpi_send_thread.py
fedml/distributed/communication/observer.py
fedml/distributed/server/__init__.py
fedml/distributed/server/server_manager.py
fedml/distributed/topology/__init__.py
fedml/distributed/topology/topology_manager.py
fedml_core-0.9.1.dist-info/LICENSE
fedml_core-0.9.1.dist-info/METADATA
fedml_core-0.9.1.dist-info/WHEEL
fedml_core-0.9.1.dist-info/top_level.txt
fedml_core-0.9.1.dist-info/RECORD
