Metadata-Version: 2.1
Name: fedml-core
Version: 0.9.1
Summary: FedML
Home-page: https://github.com/chaoyanghe/fedml
Author: Chaoyang He
Author-email: chaoyanghe.com@gmail.com
License: UNKNOWN
Platform: UNKNOWN
Classifier: Programming Language :: Python :: 3
Classifier: License :: OSI Approved :: MIT License
Classifier: Operating System :: OS Independent
Requires-Python: >=3.6
